codes/__init__.py
codes/hamed.py
myk-0.0.13.dist-info/METADATA
myk-0.0.13.dist-info/WHEEL
myk-0.0.13.dist-info/top_level.txt
myk-0.0.13.dist-info/RECORD
