Metadata-Version: 2.1
Name: myk
Version: 0.0.13
Summary: Streaming video data via networks
Home-page: UNKNOWN
Author: matari
Author-email: <mail@neuralnine.com>
License: UNKNOWN
Platform: UNKNOWN
Classifier: Development Status :: 1 - Planning
Classifier: Intended Audience :: Developers
Classifier: Programming Language :: Python :: 3
Classifier: Operating System :: Unix
Classifier: Operating System :: MacOS :: MacOS X
Classifier: Operating System :: Microsoft :: Windows
Requires-Dist: requests
